LICENSE
README.md
setup.py
pybioanalyzer/__init__.py
pybioanalyzer/main.py
pybioanalyzer.egg-info/PKG-INFO
pybioanalyzer.egg-info/SOURCES.txt
pybioanalyzer.egg-info/dependency_links.txt
pybioanalyzer.egg-info/entry_points.txt
pybioanalyzer.egg-info/requires.txt
pybioanalyzer.egg-info/top_level.txt