Metadata-Version: 2.1
Name: pybioanalyzer
Version: 0.1
Summary: A Python parser for Bioanalyzer files
Home-page: https://github.com/Shunsuke-1994/PyBioAnalyzer
Author: Shunsuke Sumi, Evgeniia Edeleva, Georg Urtel
Author-email: shunsuke.sumi@cira.kyoto-u.ac.jp
License: MIT
Requires-Python: >=3.7.0
License-File: LICENSE
